CHANGES.rst
CONTRIBUTORS.rst
DEVELOP.rst
LICENSE.rst
MANIFEST.in
README.rst
setup.cfg
setup.py
docs/conf.py
docs/index.rst
src/collective/__init__.py
src/collective.excludefromcollection.egg-info/PKG-INFO
src/collective.excludefromcollection.egg-info/SOURCES.txt
src/collective.excludefromcollection.egg-info/dependency_links.txt
src/collective.excludefromcollection.egg-info/entry_points.txt
src/collective.excludefromcollection.egg-info/namespace_packages.txt
src/collective.excludefromcollection.egg-info/not-zip-safe
src/collective.excludefromcollection.egg-info/requires.txt
src/collective.excludefromcollection.egg-info/top_level.txt
src/collective/excludefromcollection/__init__.py
src/collective/excludefromcollection/configure.zcml
src/collective/excludefromcollection/interfaces.py
src/collective/excludefromcollection/permissions.zcml
src/collective/excludefromcollection/setuphandlers.py
src/collective/excludefromcollection/testing.py
src/collective/excludefromcollection/behaviors/__init__.py
src/collective/excludefromcollection/behaviors/configure.zcml
src/collective/excludefromcollection/behaviors/exclude_from_collection.py
src/collective/excludefromcollection/browser/__init__.py
src/collective/excludefromcollection/browser/configure.zcml
src/collective/excludefromcollection/browser/overrides/.gitkeep
src/collective/excludefromcollection/browser/static/.gitkeep
src/collective/excludefromcollection/indexers/__init__.py
src/collective/excludefromcollection/indexers/configure.zcml
src/collective/excludefromcollection/indexers/exclude_from_collection.py
src/collective/excludefromcollection/indexers/exclude_from_collection.zcml
src/collective/excludefromcollection/locales/README.rst
src/collective/excludefromcollection/locales/__init__.py
src/collective/excludefromcollection/locales/collective.excludefromcollection.pot
src/collective/excludefromcollection/locales/update.py
src/collective/excludefromcollection/locales/update.sh
src/collective/excludefromcollection/locales/__pycache__/LC_MESSAGES/collective.excludefromcollection.po
src/collective/excludefromcollection/locales/de/LC_MESSAGES/collective.excludefromcollection.po
src/collective/excludefromcollection/locales/en/LC_MESSAGES/collective.excludefromcollection.po
src/collective/excludefromcollection/profiles/default/browserlayer.xml
src/collective/excludefromcollection/profiles/default/catalog.xml
src/collective/excludefromcollection/profiles/default/metadata.xml
