Metadata-Version: 2.1
Name: collective.excludefromcollection
Version: 1.1
Summary: Provides a behavior to conditionally exclude an object from a Plone Collection.
Home-page: https://github.com/collective/collective.excludefromcollection
Author: Maik Derstappen
Author-email: md@derico.de
License: GPL version 2
Project-URL: PyPI, https://pypi.python.org/pypi/collective.excludefromcollection
Project-URL: Source, https://github.com/collective/collective.excludefromcollection
Project-URL: Tracker, https://github.com/collective/collective.excludefromcollection/issues
Keywords: Python Plone CMS
Platform: UNKNOWN
Classifier: Environment :: Web Environment
Classifier: Framework :: Plone
Classifier: Framework :: Plone :: Addon
Classifier: Framework :: Plone :: 5.2
Classifier: Framework :: Plone :: 6.0
Classifier: Programming Language :: Python
Classifier: Programming Language :: Python :: 3.7
Classifier: Programming Language :: Python :: 3.8
Classifier: Programming Language :: Python :: 3.9
Classifier: Operating System :: OS Independent
Classifier: License :: OSI Approved :: GNU General Public License v2 (GPLv2)
Requires-Python: >=3.7
Provides-Extra: test
